{
  "title": "Solo Leveling S02e12 Are You The King Of Humans",
  "cname1": "StreamP2P",
  "link1": "https://animeplay.strp2p.live/#18bob",
  "cname2": "RPMShare",
  "link2": "https://aniflix.rpmvip.com/#t5qri",
  "cname3": "EarnVids",
  "link3": "https://Smoothpre.com/embed/0gswn8lblbcj",
  "cname4": "StreamHG",
  "link4": "https://cybervynx.com/e/b6es9o26wr3z",
  "cname5": "Hydrax",
  "link5": "https://short.icu/D3IPaFZDs-",
  "cname6": "KrakenFiles",
  "link6": "https://krakenfiles.com/embed-video/Xc2ss3JKUL",
  "cname7": "StreamRuby",
  "link7": "https://rubyvidhub.com/embed-480aeaqweeam.html",
  "cname8": "UpnShare",
  "link8": "https://aniflix.uns.wtf/#djzftg",
  "cname9": "FileMoon",
  "link9": "https://filemoon.to/e/9qgnae9r769i",
  "dname1": "KrakenFiles",
  "dlink1": "https://krakenfiles.com/view/Xc2ss3JKUL/file.html",
  "dname2": "GDToT",
  "dlink2": "https://new17.gdtot.dad/file/21189724998",
  "dname3": "Send",
  "dlink3": "https://send.cm/u6qxpvmjexqf",
  "dname4": "FileMoon",
  "dlink4": "https://filemoon.to/d/9qgnae9r769i",
  "dname5": "FilePress",
  "dlink5": "https://filepress.ink/file/67fe76abbdafa4d9cbcc62e5"
}