{
  "title": "Re Zero Starting Another World S03e15 10bit Esub",
  "cname1": "Hydrax",
  "link1": "https://short.icu/wMaJXY8cq",
  "cname2": "EarnVids",
  "link2": "https://Smoothpre.com/embed/phehycxkqpfs",
  "cname3": "FileMoon",
  "link3": "https://filemoon.in/e/vrp43qtbje2s",
  "dname1": "FileMoon",
  "dlink1": "https://filemoon.in/d/vrp43qtbje2s",
  "cname4": "RPMShare",
  "link4": "https://aniflix.rpmvip.com/#ne8k6",
  "cname5": "KrakenFiles",
  "link5": "https://krakenfiles.com/embed-video/WZgdWlHFyz",
  "dname2": "KrakenFiles",
  "dlink2": "https://krakenfiles.com/view/WZgdWlHFyz/file.html",
  "cname6": "StreamRuby",
  "link6": "https://rubyvidhub.com/embed-gcodv1s0ca8j.html",
  "cname7": "UpnShare",
  "link7": "https://aniflix.uns.wtf/#isjybb",
  "cname8": "StreamP2P",
  "link8": "https://animeplay.strp2p.live/#kbxjv",
  "cname9": "StreamHG",
  "link9": "https://cybervynx.com/e/m7gomhqfkkz6",
  "dname3": "Send",
  "dlink3": "https://send.cm/8c3pxz4fcpo4",
  "dname4": "FilePress",
  "dlink4": "https://filepress.ink/file/680116e7bdafa4d9cb7879e3",
  "dname5": "GDToT",
  "dlink5": "https://new17.gdtot.dad/file/3872700543"
}