{
  "title": "Overlord S02e11 Jap Esub Com",
  "cname1": "Hydrax",
  "link1": "https://short.icu/RcOdOMuFi",
  "cname2": "EarnVids",
  "link2": "https://Smoothpre.com/embed/skvy448ia135",
  "cname3": "FileMoon",
  "link3": "https://filemoon.in/e/0zp8oce0redv",
  "dname1": "FileMoon",
  "dlink1": "https://filemoon.in/d/0zp8oce0redv",
  "cname4": "RPMShare",
  "link4": "https://aniflix.rpmvip.com/#uzrro",
  "cname5": "KrakenFiles",
  "link5": "https://krakenfiles.com/embed-video/ZkffzMltnD",
  "dname2": "KrakenFiles",
  "dlink2": "https://krakenfiles.com/view/ZkffzMltnD/file.html",
  "cname6": "StreamRuby",
  "link6": "https://rubyvidhub.com/embed-mz5xqneg864f.html",
  "cname7": "UpnShare",
  "link7": "https://animeplay.upns.live/#pkvugk",
  "cname8": "StreamP2P",
  "link8": "https://animeplay.strp2p.live/#3o1sr",
  "cname9": "StreamHG",
  "link9": "https://cybervynx.com/e/ezsw8gf0b37c",
  "dname3": "Send",
  "dlink3": "https://send.cm/769wloyatmb6",
  "dname4": "FilePress",
  "dlink4": "https://filepress.ink/file/6810edf48d595a25fe36d208",
  "dname5": "GDToT",
  "dlink5": "https://new17.gdtot.dad/file/821216946"
}